py_imu/__init__.py
py_imu/__main__.py
py_imu/definitions.py
py_imu/fusion/__init__.py
py_imu/fusion/madgwick.py
py_imu/fusion/motion.py
py_imu/fusion/quaternion.py
py_imu/fusion/utilities.py
py_imu/utils.py
py_imu-0.1.0.dist-info/LICENSE
py_imu-0.1.0.dist-info/METADATA
py_imu-0.1.0.dist-info/WHEEL
py_imu-0.1.0.dist-info/RECORD
