Metadata-Version: 2.3
Name: py-imu
Version: 0.1.0
Summary: Madgwick filter for IMU data and quaternions.
Author: Tsmorz
Author-email: tony.smoragiewicz@tum.de
Requires-Python: >=3.11,<3.13
Classifier: Programming Language :: Python :: 3
Classifier: Programming Language :: Python :: 3.11
Classifier: Programming Language :: Python :: 3.12
Requires-Dist: loguru (>=0.7.3,<0.8.0)
Requires-Dist: numpy (>=2.2.3,<3.0.0)
Project-URL: homepage, https://github.com/TUM-Aries-Lab/py-imu
